sqlalchemy_enum34.py
SQLAlchemy_Enum34-2.0.0.dist-info/LICENSE
SQLAlchemy_Enum34-2.0.0.dist-info/METADATA
SQLAlchemy_Enum34-2.0.0.dist-info/WHEEL
SQLAlchemy_Enum34-2.0.0.dist-info/top_level.txt
SQLAlchemy_Enum34-2.0.0.dist-info/RECORD
