Metadata-Version: 2.1
Name: SQLAlchemy-Enum34
Version: 2.0.0
Summary: SQLAlchemy type to store standard enum.Enum value
Home-page: https://github.com/spoqa/sqlalchemy-enum34
Author: Hong Minhee
Author-email: hongminhee@member.fsf.org
License: MIT License
Platform: UNKNOWN
Classifier: Development Status :: 5 - Production/Stable
Classifier: Intended Audience :: Developers
Classifier: License :: OSI Approved :: MIT License
Classifier: Operating System :: OS Independent
Classifier: Programming Language :: Python :: 2.7
Classifier: Programming Language :: Python :: 3.6
Classifier: Programming Language :: Python :: 3.7
Classifier: Programming Language :: Python :: 3.8
Classifier: Programming Language :: Python :: 3.9
Classifier: Programming Language :: Python :: Implementation :: CPython
Classifier: Programming Language :: Python :: Implementation :: PyPy
Classifier: Programming Language :: Python :: Implementation :: Stackless
Classifier: Programming Language :: SQL
Classifier: Topic :: Database :: Front-Ends
Classifier: Topic :: Software Development
Requires-Dist: SQLAlchemy (>=1.3.0)
